[
  {
    "product_id": 6,
    "TurkishName": "Ayva",
    "EnglishName": "Quince",
    "TurkishCategory": "Meyve",
    "EnglishCategory": "Fruit",
    "category_id": 21
  },
  {
    "TurkishName": "Süt",
    "EnglishName": "Milk",
    "TurkishCategory": "Reçel, Bal ve Sürülebilir Ürünler",
    "EnglishCategory": "Jam, Honey & Spreads",
    "category_id": 24
  },
  {
    "TurkishName": "Zeytinyağı",
    "EnglishName": "Olive oil",
    "TurkishCategory": "Sıvı Yağlar",
    "EnglishCategory": "Oils",
    "category_id": 27
  }
]